asyncur/__init__.py
asyncur/aio.py
asyncur/client.py
asyncur/exceptions.py
asyncur/py.typed
asyncur/timing.py
asyncur/utils.py
asyncur/xls.py
asyncur-0.5.4.dist-info/LICENSE
asyncur-0.5.4.dist-info/METADATA
asyncur-0.5.4.dist-info/WHEEL
asyncur-0.5.4.dist-info/RECORD
