Metadata-Version: 2.1
Name: asyncur
Version: 0.5.4
Summary: Async functions to compare with anyio and asyncio, and toolkit to read excel with async/await.
Author: Waket Zheng
Author-email: waketzheng@gmail.com
Requires-Python: >=3.10,<4.0
Classifier: Programming Language :: Python :: 3
Classifier: Programming Language :: Python :: 3.10
Classifier: Programming Language :: Python :: 3.11
Classifier: Programming Language :: Python :: 3.12
Provides-Extra: xls
Requires-Dist: anyio (>=3.7.1)
Requires-Dist: openpyxl (>=3.1.4,<4.0.0) ; extra == "xls"
Requires-Dist: pandas (>=2.2.2,<3.0.0) ; extra == "xls"
Requires-Dist: redis (>=5.0.0)
